psychopumpum/__init__.py
psychopumpum-1.1.0.dist-info/METADATA
psychopumpum-1.1.0.dist-info/WHEEL
psychopumpum-1.1.0.dist-info/entry_points.txt
psychopumpum-1.1.0.dist-info/top_level.txt
psychopumpum-1.1.0.dist-info/RECORD
