Metadata-Version: 2.1
Name: psychopumpum
Version: 1.1.0
Summary: Read the latest Real Python tutorials
Home-page: https://github.com/psychopumpum/psychopumpum-api
Author: psychopumpum
Author-email: fadhil@rhyn.tech
License: MIT
Platform: UNKNOWN
Classifier: License :: OSI Approved :: MIT License
Classifier: Programming Language :: Python :: 3
Requires-Dist: requests
